quantstratforge/__init__.py
quantstratforge/backtester.py
quantstratforge/cli.py
quantstratforge/data_prep.py
quantstratforge/generator.py
quantstratforge/model.py
quantstratforge/optimizer.py
quantstratforge/utils.py
quantstratforge-0.2.1.dist-info/METADATA
quantstratforge-0.2.1.dist-info/WHEEL
quantstratforge-0.2.1.dist-info/entry_points.txt
quantstratforge-0.2.1.dist-info/licenses/LICENSE
quantstratforge-0.2.1.dist-info/RECORD
