Metadata-Version: 2.4
Name: quantstratforge
Version: 0.2.1
Summary: Privacy-preserving agentic SLM for quant strategy forging
License: Apache-2.0
License-File: LICENSE
Keywords: quantitative,trading,ai,machine-learning,finance,privacy,federated-learning
Author: QuantStratForge Team
Requires-Python: >=3.12,<4.0
Classifier: Development Status :: 4 - Beta
Classifier: Intended Audience :: Developers
Classifier: Intended Audience :: Financial and Insurance Industry
Classifier: License :: OSI Approved :: Apache Software License
Classifier: Programming Language :: Python :: 3
Classifier: Programming Language :: Python :: 3.12
Classifier: Programming Language :: Python :: 3.13
Classifier: Programming Language :: Python :: 3.14
Classifier: Topic :: Office/Business :: Financial :: Investment
Classifier: Topic :: Scientific/Engineering :: Artificial Intelligence
Requires-Dist: accelerate (>=0.21.0,<2.0.0)
Requires-Dist: bitsandbytes (>=0.41.0,<1.0.0)
Requires-Dist: datasets (>=2.14.0,<3.0.0)
Requires-Dist: fastapi (>=0.95.0,<1.0.0)
Requires-Dist: flower (>=2.0.0,<3.0.0)
Requires-Dist: flwr (>=1.8.0,<2.0.0)
Requires-Dist: huggingface_hub (>=0.17.0,<1.0.0)
Requires-Dist: peft (>=0.5.0,<1.0.0)
Requires-Dist: torch (>=2.0.0,<3.0.0)
Requires-Dist: transformers (>=4.38.0,<5.0.0)
Requires-Dist: uvicorn (>=0.22.0,<1.0.0)
Requires-Dist: websockets (>=12.0.0,<16.0.0)
Requires-Dist: yfinance (>=0.2.0,<1.0.0)
Project-URL: Homepage, https://github.com/quantstratforge/quantstratforge
Project-URL: Repository, https://github.com/quantstratforge/quantstratforge
